{"latitude":50.296256,"longitude":-117.68575,"timezone":"America\/Vancouver","offset":-7,"currently":{"time":1497137253,"summary":"Drizzle","icon":"rain","nearestStormDistance":0,"precipIntensity":0.2769,"precipProbability":0.52,"precipType":"rain","temperature":9.78,"apparentTemperature":8.69,"dewPoint":3.58,"humidity":0.65,"windSpeed":2.32,"windBearing":296,"visibility":15.61,"cloudCover":0.94,"pressure":1005.52,"ozone":338.22},"hourly":{"summary":"Light rain until this evening.","icon":"rain","data":[{"time":1497135600,"summary":"Light Rain","icon":"rain","precipIntensity":0.2794,"precipProbability":0.52,"precipType":"rain","temperature":10.12,"apparentTemperature":10.12,"dewPoint":3.78,"humidity":0.65,"windSpeed":2.19,"windBearing":295,"visibility":15.55,"cloudCover":0.96,"pressure":1005.68,"ozone":338},{"time":1497139200,"summary":"Light Rain","icon":"rain","precipIntensity":0.2718,"precipProbability":0.52,"precipType":"rain","temperature":9.38,"apparentTemperature":8.11,"dewPoint":3.33,"humidity":0.66,"windSpeed":2.47,"windBearing":296,"visibility":15.69,"cloudCover":0.92,"pressure":1005.33,"ozone":338.48},{"time":1497142800,"summary":"Drizzle","icon":"rain","precipIntensity":0.2261,"precipProbability":0.47,"precipType":"rain","temperature":9.86,"apparentTemperature":8.9,"dewPoint":4.18,"humidity":0.68,"windSpeed":2.15,"windBearing":300,"visibility":15.64,"cloudCover":0.85,"pressure":1005.49,"ozone":339.11},{"time":1497146400,"summary":"Drizzle","icon":"rain","precipIntensity":0.1702,"precipProbability":0.32,"precipType":"rain","temperature":9.62,"apparentTemperature":8.82,"dewPoint":4.57,"humidity":0.71,"windSpeed":1.91,"windBearing":299,"visibility":15.47,"cloudCover":0.77,"pressure":1005.9,"ozone":339.74},{"time":1497150000,"summary":"Mostly Cloudy","icon":"partly-cloudy-day","precipIntensity":0.0864,"precipProbability":0.12,"precipType":"rain","temperature":8.64,"apparentTemperature":7.89,"dewPoint":4.27,"humidity":0.74,"windSpeed":1.69,"windBearing":293,"visibility":15.26,"cloudCover":0.71,"pressure":1006.45,"ozone":339.68},{"time":1497153600,"summary":"Mostly Cloudy","icon":"partly-cloudy-night","precipIntensity":0.0432,"precipProbability":0.04,"precipType":"rain","temperature":7.32,"apparentTemperature":6.67,"dewPoint":3.63,"humidity":0.77,"windSpeed":1.43,"windBearing":284,"visibility":15.3,"cloudCover":0.68,"pressure":1007.05,"ozone":338.47},{"time":1497157200,"summary":"Mostly Cloudy","icon":"partly-cloudy-night","precipIntensity":0.033,"precipProbability":0.02,"precipType":"rain","temperature":6.23,"apparentTemperature":6.23,"dewPoint":3.3,"humidity":0.82,"windSpeed":1.09,"windBearing":271,"visibility":15.53,"cloudCover":0.65,"pressure":1007.86,"ozone":336.58},{"time":1497160800,"summary":"Mostly Cloudy","icon":"partly-cloudy-night","precipIntensity":0.0305,"precipProbability":0.02,"precipType":"rain","temperature":5.53,"apparentTemperature":5.53,"dewPoint":3.11,"humidity":0.84,"windSpeed":0.95,"windBearing":267,"visibility":15.51,"cloudCover":0.65,"pressure":1008.55,"ozone":334.7},{"time":1497164400,"summary":"Mostly Cloudy","icon":"partly-cloudy-night","precipIntensity":0.0229,"precipProbability":0.01,"precipType":"rain","temperature":5.33,"apparentTemperature":5.33,"dewPoint":3.27,"humidity":0.87,"windSpeed":0.86,"windBearing":261,"visibility":14.68,"cloudCover":0.71,"pressure":1009.18,"ozone":332.95},{"time":1497168000,"summary":"Mostly Cloudy","icon":"partly-cloudy-night","precipIntensity":0,"precipProbability":0,"temperature":5.23,"apparentTemperature":5.23,"dewPoint":3.45,"humidity":0.88,"windSpeed":0.69,"windBearing":254,"visibility":13.39,"cloudCover":0.79,"pressure":1009.79,"ozone":331.23},{"time":1497171600,"summary":"Mostly Cloudy","icon":"partly-cloudy-night","precipIntensity":0,"precipProbability":0,"temperature":5.13,"apparentTemperature":5.13,"dewPoint":3.58,"humidity":0.9,"windSpeed":0.59,"windBearing":249,"visibility":12.46,"cloudCover":0.83,"pressure":1010.36,"ozone":329.93},{"time":1497175200,"summary":"Mostly Cloudy","icon":"partly-cloudy-night","precipIntensity":0,"precipProbability":0,"temperature":4.69,"apparentTemperature":4.69,"dewPoint":3.38,"humidity":0.91,"windSpeed":0.53,"windBearing":249,"visibility":12.25,"cloudCover":0.78,"pressure":1010.9,"ozone":329.47},{"time":1497178800,"summary":"Mostly Cloudy","icon":"partly-cloudy-night","precipIntensity":0,"precipProbability":0,"temperature":4.23,"apparentTemperature":4.23,"dewPoint":3.11,"humidity":0.92,"windSpeed":0.47,"windBearing":252,"visibility":12.36,"cloudCover":0.68,"pressure":1011.38,"ozone":329.45},{"time":1497182400,"summary":"Mostly Cloudy","icon":"partly-cloudy-day","precipIntensity":0,"precipProbability":0,"temperature":4.33,"apparentTemperature":4.33,"dewPoint":3.19,"humidity":0.92,"windSpeed":0.47,"windBearing":251,"visibility":12.52,"cloudCover":0.62,"pressure":1011.75,"ozone":329.08},{"time":1497186000,"summary":"Mostly Cloudy","icon":"partly-cloudy-day","precipIntensity":0,"precipProbability":0,"temperature":5.46,"apparentTemperature":5.46,"dewPoint":4.01,"humidity":0.9,"windSpeed":0.59,"windBearing":243,"visibility":12.55,"cloudCover":0.63,"pressure":1011.98,"ozone":328.03},{"time":1497189600,"summary":"Mostly Cloudy","icon":"partly-cloudy-day","precipIntensity":0,"precipProbability":0,"temperature":6.93,"apparentTemperature":6.93,"dewPoint":4.91,"humidity":0.87,"windSpeed":0.88,"windBearing":238,"visibility":12.65,"cloudCover":0.66,"pressure":1012.1,"ozone":326.63},{"time":1497193200,"summary":"Mostly Cloudy","icon":"partly-cloudy-day","precipIntensity":0,"precipProbability":0,"temperature":8.59,"apparentTemperature":8.59,"dewPoint":5.86,"humidity":0.83,"windSpeed":1.15,"windBearing":242,"visibility":12.94,"cloudCover":0.69,"pressure":1012.1,"ozone":325.16},{"time":1497196800,"summary":"Mostly Cloudy","icon":"partly-cloudy-day","precipIntensity":0,"precipProbability":0,"temperature":10.36,"apparentTemperature":10.36,"dewPoint":6.76,"humidity":0.78,"windSpeed":1.32,"windBearing":252,"visibility":13.87,"cloudCover":0.68,"pressure":1011.94,"ozone":323.52},{"time":1497200400,"summary":"Mostly Cloudy","icon":"partly-cloudy-day","precipIntensity":0,"precipProbability":0,"temperature":11.74,"apparentTemperature":11.74,"dewPoint":7.22,"humidity":0.74,"windSpeed":1.43,"windBearing":263,"visibility":15.08,"cloudCover":0.67,"pressure":1011.7,"ozone":321.81},{"time":1497204000,"summary":"Mostly Cloudy","icon":"partly-cloudy-day","precipIntensity":0,"precipProbability":0,"temperature":13.09,"apparentTemperature":13.09,"dewPoint":7.57,"humidity":0.69,"windSpeed":1.52,"windBearing":269,"visibility":16.09,"cloudCover":0.65,"pressure":1011.43,"ozone":320.58},{"time":1497207600,"summary":"Mostly Cloudy","icon":"partly-cloudy-day","precipIntensity":0,"precipProbability":0,"temperature":14.47,"apparentTemperature":14.47,"dewPoint":7.89,"humidity":0.65,"windSpeed":1.53,"windBearing":270,"visibility":16.09,"cloudCover":0.66,"pressure":1011.06,"ozone":320.26},{"time":1497211200,"summary":"Mostly Cloudy","icon":"partly-cloudy-day","precipIntensity":0,"precipProbability":0,"temperature":15.84,"apparentTemperature":15.84,"dewPoint":8.19,"humidity":0.6,"windSpeed":1.5,"windBearing":268,"visibility":16.09,"cloudCover":0.67,"pressure":1010.62,"ozone":320.42},{"time":1497214800,"summary":"Mostly Cloudy","icon":"partly-cloudy-day","precipIntensity":0,"precipProbability":0,"temperature":17.23,"apparentTemperature":17.23,"dewPoint":8.83,"humidity":0.58,"windSpeed":1.4,"windBearing":274,"visibility":16.09,"cloudCover":0.68,"pressure":1010.21,"ozone":320.37},{"time":1497218400,"summary":"Mostly Cloudy","icon":"partly-cloudy-day","precipIntensity":0,"precipProbability":0,"temperature":17.73,"apparentTemperature":17.73,"dewPoint":9.25,"humidity":0.58,"windSpeed":1.41,"windBearing":286,"visibility":16.09,"cloudCover":0.69,"pressure":1009.86,"ozone":319.72},{"time":1497222000,"summary":"Mostly Cloudy","icon":"partly-cloudy-day","precipIntensity":0,"precipProbability":0,"temperature":17.65,"apparentTemperature":17.65,"dewPoint":9.56,"humidity":0.59,"windSpeed":1.65,"windBearing":309,"visibility":16.09,"cloudCover":0.68,"pressure":1009.59,"ozone":318.86},{"time":1497225600,"summary":"Mostly Cloudy","icon":"partly-cloudy-day","precipIntensity":0,"precipProbability":0,"temperature":17.13,"apparentTemperature":17.13,"dewPoint":9.63,"humidity":0.61,"windSpeed":1.9,"windBearing":319,"visibility":16.09,"cloudCover":0.64,"pressure":1009.43,"ozone":318.27},{"time":1497229200,"summary":"Partly Cloudy","icon":"partly-cloudy-day","precipIntensity":0,"precipProbability":0,"temperature":15.97,"apparentTemperature":15.97,"dewPoint":9.29,"humidity":0.65,"windSpeed":1.91,"windBearing":319,"visibility":16.09,"cloudCover":0.54,"pressure":1009.39,"ozone":318.15},{"time":1497232800,"summary":"Partly Cloudy","icon":"partly-cloudy-day","precipIntensity":0,"precipProbability":0,"temperature":14.46,"apparentTemperature":14.46,"dewPoint":8.79,"humidity":0.69,"windSpeed":1.67,"windBearing":317,"visibility":16.09,"cloudCover":0.39,"pressure":1009.48,"ozone":318.31},{"time":1497236400,"summary":"Partly Cloudy","icon":"partly-cloudy-day","precipIntensity":0,"precipProbability":0,"temperature":12.74,"apparentTemperature":12.74,"dewPoint":8.03,"humidity":0.73,"windSpeed":1.31,"windBearing":319,"visibility":16.09,"cloudCover":0.27,"pressure":1009.69,"ozone":318.57},{"time":1497240000,"summary":"Clear","icon":"clear-night","precipIntensity":0,"precipProbability":0,"temperature":10.76,"apparentTemperature":10.76,"dewPoint":6.95,"humidity":0.77,"windSpeed":0.97,"windBearing":326,"visibility":16.09,"cloudCover":0.21,"pressure":1010.1,"ozone":318.89},{"time":1497243600,"summary":"Clear","icon":"clear-night","precipIntensity":0,"precipProbability":0,"temperature":8.86,"apparentTemperature":8.86,"dewPoint":5.89,"humidity":0.82,"windSpeed":0.65,"windBearing":341,"visibility":16.09,"cloudCover":0.19,"pressure":1010.59,"ozone":319.33},{"time":1497247200,"summary":"Clear","icon":"clear-night","precipIntensity":0,"precipProbability":0,"temperature":7.44,"apparentTemperature":7.44,"dewPoint":5.09,"humidity":0.85,"windSpeed":0.52,"windBearing":8,"visibility":16.09,"cloudCover":0.18,"pressure":1010.86,"ozone":319.81},{"time":1497250800,"summary":"Clear","icon":"clear-night","precipIntensity":0,"precipProbability":0,"temperature":6.64,"apparentTemperature":6.64,"dewPoint":4.66,"humidity":0.87,"windSpeed":0.56,"windBearing":28,"visibility":14.84,"cloudCover":0.2,"pressure":1010.71,"ozone":320.28},{"time":1497254400,"summary":"Partly Cloudy","icon":"partly-cloudy-night","precipIntensity":0,"precipProbability":0,"temperature":6.31,"apparentTemperature":6.31,"dewPoint":4.56,"humidity":0.89,"windSpeed":0.65,"windBearing":36,"visibility":13.13,"cloudCover":0.25,"pressure":1010.35,"ozone":320.8},{"time":1497258000,"summary":"Partly Cloudy","icon":"partly-cloudy-night","precipIntensity":0,"precipProbability":0,"temperature":6.08,"apparentTemperature":6.08,"dewPoint":4.52,"humidity":0.9,"windSpeed":0.75,"windBearing":39,"visibility":11.89,"cloudCover":0.29,"pressure":1010.09,"ozone":321.48},{"time":1497261600,"summary":"Partly Cloudy","icon":"partly-cloudy-night","precipIntensity":0,"precipProbability":0,"temperature":5.41,"apparentTemperature":5.41,"dewPoint":4.14,"humidity":0.92,"windSpeed":0.84,"windBearing":47,"visibility":11.46,"cloudCover":0.34,"pressure":1010.15,"ozone":322.4},{"time":1497265200,"summary":"Partly Cloudy","icon":"partly-cloudy-night","precipIntensity":0,"precipProbability":0,"temperature":4.75,"apparentTemperature":4.75,"dewPoint":3.73,"humidity":0.93,"windSpeed":0.97,"windBearing":57,"visibility":11.49,"cloudCover":0.4,"pressure":1010.33,"ozone":323.48},{"time":1497268800,"summary":"Partly Cloudy","icon":"partly-cloudy-day","precipIntensity":0,"precipProbability":0,"temperature":5.16,"apparentTemperature":5.16,"dewPoint":4.02,"humidity":0.92,"windSpeed":1.01,"windBearing":58,"visibility":11.99,"cloudCover":0.42,"pressure":1010.34,"ozone":324.52},{"time":1497272400,"summary":"Partly Cloudy","icon":"partly-cloudy-day","precipIntensity":0,"precipProbability":0,"temperature":7.43,"apparentTemperature":7.43,"dewPoint":5.52,"humidity":0.88,"windSpeed":0.9,"windBearing":50,"visibility":13.21,"cloudCover":0.35,"pressure":1009.97,"ozone":325.43},{"time":1497276000,"summary":"Clear","icon":"clear-day","precipIntensity":0,"precipProbability":0,"temperature":10.48,"apparentTemperature":10.48,"dewPoint":7.33,"humidity":0.81,"windSpeed":0.78,"windBearing":35,"visibility":14.89,"cloudCover":0.23,"pressure":1009.4,"ozone":326.3},{"time":1497279600,"summary":"Clear","icon":"clear-day","precipIntensity":0,"precipProbability":0,"temperature":12.67,"apparentTemperature":12.67,"dewPoint":8.23,"humidity":0.74,"windSpeed":0.65,"windBearing":15,"visibility":16.09,"cloudCover":0.16,"pressure":1008.78,"ozone":327.22},{"time":1497283200,"summary":"Clear","icon":"clear-day","precipIntensity":0,"precipProbability":0,"temperature":15.04,"apparentTemperature":15.04,"dewPoint":9.45,"humidity":0.69,"windSpeed":0.68,"windBearing":344,"visibility":16.09,"cloudCover":0.18,"pressure":1008.13,"ozone":328.23},{"time":1497286800,"summary":"Partly Cloudy","icon":"partly-cloudy-day","precipIntensity":0,"precipProbability":0,"temperature":17.24,"apparentTemperature":17.24,"dewPoint":10.51,"humidity":0.65,"windSpeed":0.9,"windBearing":319,"visibility":16.09,"cloudCover":0.25,"pressure":1007.47,"ozone":329.29},{"time":1497290400,"summary":"Partly Cloudy","icon":"partly-cloudy-day","precipIntensity":0,"precipProbability":0,"temperature":19.09,"apparentTemperature":19.09,"dewPoint":11.31,"humidity":0.61,"windSpeed":1.16,"windBearing":311,"visibility":16.09,"cloudCover":0.31,"pressure":1006.86,"ozone":330.31},{"time":1497294000,"summary":"Partly Cloudy","icon":"partly-cloudy-day","precipIntensity":0,"precipProbability":0,"temperature":20.57,"apparentTemperature":20.57,"dewPoint":11.86,"humidity":0.57,"windSpeed":1.46,"windBearing":310,"visibility":16.09,"cloudCover":0.35,"pressure":1006.32,"ozone":331.45},{"time":1497297600,"summary":"Partly Cloudy","icon":"partly-cloudy-day","precipIntensity":0,"precipProbability":0,"temperature":21.62,"apparentTemperature":21.62,"dewPoint":12.12,"humidity":0.55,"windSpeed":1.72,"windBearing":311,"visibility":16.09,"cloudCover":0.37,"pressure":1005.82,"ozone":332.56},{"time":1497301200,"summary":"Partly Cloudy","icon":"partly-cloudy-day","precipIntensity":0,"precipProbability":0,"temperature":22.08,"apparentTemperature":22.08,"dewPoint":12.05,"humidity":0.53,"windSpeed":1.95,"windBearing":311,"visibility":16.09,"cloudCover":0.38,"pressure":1005.28,"ozone":333.12},{"time":1497304800,"summary":"Partly Cloudy","icon":"partly-cloudy-day","precipIntensity":0,"precipProbability":0,"temperature":21.95,"apparentTemperature":21.95,"dewPoint":11.68,"humidity":0.52,"windSpeed":2.28,"windBearing":310,"visibility":15.98,"cloudCover":0.33,"pressure":1004.63,"ozone":332.72},{"time":1497308400,"summary":"Partly Cloudy","icon":"partly-cloudy-day","precipIntensity":0,"precipProbability":0,"temperature":21.34,"apparentTemperature":21.34,"dewPoint":11.17,"humidity":0.52,"windSpeed":2.57,"windBearing":309,"visibility":15.84,"cloudCover":0.25,"pressure":1003.95,"ozone":331.76}]},"daily":{"summary":"Light rain throughout the week, with temperatures rising to 22\u00b0C on Monday.","icon":"rain","data":[{"time":1497078000,"summary":"Light rain until evening.","icon":"rain","sunriseTime":1497094902,"sunsetTime":1497153698,"moonPhase":0.54,"precipIntensity":0.1245,"precipIntensityMax":0.3683,"precipIntensityMaxTime":1497132000,"precipProbability":0.56,"precipType":"rain","temperatureMin":3.81,"temperatureMinTime":1497092400,"temperatureMax":10.12,"temperatureMaxTime":1497135600,"apparentTemperatureMin":2.56,"apparentTemperatureMinTime":1497099600,"apparentTemperatureMax":10.12,"apparentTemperatureMaxTime":1497135600,"dewPoint":3.18,"humidity":0.77,"windSpeed":1.57,"windBearing":276,"visibility":14.82,"cloudCover":0.66,"pressure":1005.86,"ozone":341.21},{"time":1497164400,"summary":"Mostly cloudy until evening.","icon":"partly-cloudy-day","sunriseTime":1497181285,"sunsetTime":1497240138,"moonPhase":0.57,"precipIntensity":0.0051,"precipIntensityMax":0.0229,"precipIntensityMaxTime":1497164400,"precipProbability":0.01,"precipType":"rain","temperatureMin":4.23,"temperatureMinTime":1497178800,"temperatureMax":17.73,"temperatureMaxTime":1497218400,"apparentTemperatureMin":4.23,"apparentTemperatureMinTime":1497178800,"apparentTemperatureMax":17.73,"apparentTemperatureMaxTime":1497218400,"dewPoint":6.41,"humidity":0.76,"windSpeed":0.95,"windBearing":284,"visibility":14.79,"cloudCover":0.59,"pressure":1010.65,"ozone":323.28},{"time":1497250800,"summary":"Partly cloudy in the morning.","icon":"partly-cloudy-day","sunriseTime":1497267671,"sunsetTime":1497326575,"moonPhase":0.6,"precipIntensity":0,"precipIntensityMax":0,"precipProbability":0,"temperatureMin":4.75,"temperatureMinTime":1497265200,"temperatureMax":22.08,"temperatureMaxTime":1497301200,"apparentTemperatureMin":4.75,"apparentTemperatureMinTime":1497265200,"apparentTemperatureMax":22.08,"apparentTemperatureMaxTime":1497301200,"dewPoint":8.41,"humidity":0.72,"windSpeed":1.22,"windBearing":324,"visibility":15,"cloudCover":0.29,"pressure":1007.13,"ozone":327.95},{"time":1497337200,"summary":"Drizzle starting in the afternoon.","icon":"rain","sunriseTime":1497354060,"sunsetTime":1497413010,"moonPhase":0.63,"precipIntensity":0.0889,"precipIntensityMax":0.2159,"precipIntensityMaxTime":1497409200,"precipProbability":0.44,"precipType":"rain","temperatureMin":7.67,"temperatureMinTime":1497351600,"temperatureMax":19.12,"temperatureMaxTime":1497391200,"apparentTemperatureMin":7.64,"apparentTemperatureMinTime":1497358800,"apparentTemperatureMax":19.12,"apparentTemperatureMaxTime":1497391200,"dewPoint":7.93,"humidity":0.74,"windSpeed":2.69,"windBearing":301,"visibility":16.09,"cloudCover":0.47,"pressure":1008.71,"ozone":320.21},{"time":1497423600,"summary":"Light rain starting in the afternoon.","icon":"rain","sunriseTime":1497440452,"sunsetTime":1497499442,"moonPhase":0.66,"precipIntensity":0.1626,"precipIntensityMax":0.4445,"precipIntensityMaxTime":1497495600,"precipProbability":0.59,"precipType":"rain","temperatureMin":5.82,"temperatureMinTime":1497438000,"temperatureMax":16.07,"temperatureMaxTime":1497484800,"apparentTemperatureMin":5.82,"apparentTemperatureMinTime":1497438000,"apparentTemperatureMax":16.07,"apparentTemperatureMaxTime":1497484800,"dewPoint":6.02,"humidity":0.73,"windSpeed":1.19,"windBearing":231,"cloudCover":0.76,"pressure":1013.27,"ozone":335.15},{"time":1497510000,"summary":"Light rain starting in the afternoon.","icon":"rain","sunriseTime":1497526846,"sunsetTime":1497585872,"moonPhase":0.7,"precipIntensity":0.3048,"precipIntensityMax":1.1684,"precipIntensityMaxTime":1497589200,"precipProbability":0.71,"precipType":"rain","temperatureMin":5.32,"temperatureMinTime":1497528000,"temperatureMax":15.68,"temperatureMaxTime":1497560400,"apparentTemperatureMin":4.44,"apparentTemperatureMinTime":1497528000,"apparentTemperatureMax":15.68,"apparentTemperatureMaxTime":1497560400,"dewPoint":5.34,"humidity":0.74,"windSpeed":1.53,"windBearing":175,"cloudCover":0.95,"pressure":1013.74,"ozone":323.74},{"time":1497596400,"summary":"Rain throughout the day.","icon":"rain","sunriseTime":1497613244,"sunsetTime":1497672298,"moonPhase":0.73,"precipIntensity":1.2167,"precipIntensityMax":2.4308,"precipIntensityMaxTime":1497625200,"precipProbability":0.79,"precipType":"rain","temperatureMin":6.7,"temperatureMinTime":1497621600,"temperatureMax":14.08,"temperatureMaxTime":1497657600,"apparentTemperatureMin":6.7,"apparentTemperatureMinTime":1497621600,"apparentTemperatureMax":14.08,"apparentTemperatureMaxTime":1497657600,"dewPoint":8.11,"humidity":0.88,"windSpeed":1.65,"windBearing":199,"cloudCover":0.72,"pressure":1010.61,"ozone":328.58},{"time":1497682800,"summary":"Light rain until evening, starting again overnight.","icon":"rain","sunriseTime":1497699644,"sunsetTime":1497758722,"moonPhase":0.77,"precipIntensity":0.1651,"precipIntensityMax":0.574,"precipIntensityMaxTime":1497682800,"precipProbability":0.62,"precipType":"rain","temperatureMin":4.01,"temperatureMinTime":1497700800,"temperatureMax":14.69,"temperatureMaxTime":1497744000,"apparentTemperatureMin":2.81,"apparentTemperatureMinTime":1497700800,"apparentTemperatureMax":14.69,"apparentTemperatureMaxTime":1497744000,"dewPoint":4.81,"humidity":0.73,"windSpeed":1.59,"windBearing":207,"cloudCover":0.31,"pressure":1012.27,"ozone":342.14}]},"headers":["HTTP\/1.1 200 OK","Server: nginx","Date: Sat, 10 Jun 2017 23:27:33 GMT","Content-Type: application\/json; charset=utf-8","Content-Length: 20618","Connection: close","X-Forecast-API-Calls: 39","Cache-Control: max-age=3600","Expires: Sun, 11 Jun 2017 00:27:33 +0000","X-Response-Time: 74.399ms"]}